wagtail_jotform/__init__.py
wagtail_jotform/models.py
wagtail_jotform/settings.py
wagtail_jotform/utils.py
wagtail_jotform/wagtail_hooks.py
wagtail_jotform/migrations/0001_initial.py
wagtail_jotform/migrations/0002_rename_embedded_form_model.py
wagtail_jotform/migrations/__init__.py
wagtail_jotform/templates/wagtail_jotform/embedded_form_page.html
wagtail_jotform/templates/wagtail_jotform/thank_you.html
wagtail_jotform/tests/__init__.py
wagtail_jotform/tests/settings.py
wagtail_jotform/tests/tests.py
wagtail_jotform/tests/urls.py
wagtail_jotform/tests/testapp/__init__.py
wagtail_jotform-2.4.1.dist-info/METADATA
wagtail_jotform-2.4.1.dist-info/WHEEL
wagtail_jotform-2.4.1.dist-info/top_level.txt
wagtail_jotform-2.4.1.dist-info/RECORD
