Metadata-Version: 2.4
Name: wagtail-jotform
Version: 2.4.1
Summary: Embed Jotform forms in wagtail.
Home-page: https://github.com/torchbox/wagtail-jotform
Author: Kevin Howbrook
Author-email: kevin.howbrook@torchbox.com
License: BSD
Classifier: Environment :: Web Environment
Classifier: Intended Audience :: Developers
Classifier: Operating System :: OS Independent
Classifier: Programming Language :: Python
Classifier: Programming Language :: Python :: 3
Classifier: Programming Language :: Python :: 3.9
Classifier: Programming Language :: Python :: 3.10
Classifier: Programming Language :: Python :: 3.11
Classifier: Programming Language :: Python :: 3.12
Classifier: Programming Language :: Python :: 3.13
Classifier: Framework :: Wagtail
Classifier: Framework :: Wagtail :: 5
Classifier: Framework :: Wagtail :: 6
Requires-Dist: wagtail>=5.2
Provides-Extra: testing
Requires-Dist: coverage>=6.4.1; extra == "testing"
Requires-Dist: tox>=4.11.0; extra == "testing"
Provides-Extra: development
Requires-Dist: black; extra == "development"
Requires-Dist: isort; extra == "development"
Requires-Dist: flake8; extra == "development"
Requires-Dist: pre-commit; extra == "development"
Dynamic: author
Dynamic: author-email
Dynamic: classifier
Dynamic: description
Dynamic: description-content-type
Dynamic: home-page
Dynamic: license
Dynamic: provides-extra
Dynamic: requires-dist
Dynamic: summary
